Workbook

Sheet Sales by Payment Method
A1: Row Labels | B1: Sum of Total Sales
A2: Cash on Delivery | B2: 2939350
A3: Credit Card | B3: 5612350
A4: Debit Card | B4: 5658300
A5: Net Banking | B5: 2027000
A6: UPI | B6: 10000200
A7: Grand Total | B7: 26237200

Sheet Project Info
A1: PROJECT INFO - E-COMMERCE SALES DASHBOARD
A3: Project Objective
A4: To analyze e-commerce sales data and create an interactive Excel dashboard that helps identify sales performance, customer order trends, product performance, regional sales, and payment method patterns.
A6: Tools & Technologies
A7: Microsoft Excel, PivotTables, PivotCharts, Excel formulas, data cleaning, data analysis, and dashboard visualization.
A9: Dataset Description
A10: Microsoft Excel, PivotTables, PivotCharts, Excel formulas, data cleaning, data analysis, and dashboard visualization.
A12: Data Cleaning & Preparation
A13: Checked the dataset for missing values, standardized inconsistent city names such as Bangalore, Vizag, and Bombay, verified the Total Sales calculations using Quantity × Unit Price, and converted Total Sales into an Excel formula for automatic calculation.
A15: Analysis Performed
A16: Analyzed sales performance by region, category, product, month, and payment method using PivotTables and PivotCharts. Also analyzed order status to understand delivered, shipped, cancelled, and returned orders.
A18: Key Performance Indicators
... A28: Data cleaning, Excel formulas, PivotTables, PivotCharts, data analysis, KPI creation, dashboard development, data visualization, and business reporting.

Sheet Sales by Product
A1: Row Labels | B1: Sum of Total Sales
A2: Headphones | B2: 3797050
A3: Keyboard | B3: 2480700
A4: Laptop | B4: 3714750
A5: Monitor | B5: 4098950
A6: Smartphone | B6: 3150100
A7: Grand Total | B7: 17241550

Sheet E-commerce Dashboard
B1: E-COMMERCE SALES DASHBOARD
B2: TOTAL SALES | D2: TOTAL ORDERS | G2: AVERAGE ORDER VALUE | J2: CANCELLED ORDERS
B3: =SUM('Raw Data'!L2:L1201) -> 26285550 | D3: =COUNTA('Raw Data'!A2:A1201) -> 1200 | G3: =AVERAGE('Raw Data'!L2:L1201) -> 21904.625 | J3: =COUNTIF('Raw Data'!K2:K1201,"Cancelled") -> 99
B4: DELIVERED ORDERS | D4: RETURNED ORDERS | G4: SHIPPED ORDERS
B5: =COUNTIF('Raw Data'!K2:K1201,"Delivered") -> 936 | D5: =COUNTIF('Raw Data'!K2:K1201,"Returned") -> 55 | G5: =COUNTIF('Raw Data'!K2:K1201,"Shipped") -> 110

Sheet Monthly Sales Trend
A1: Row Labels | B1: Sum of Total Sales
A2: Jan | B2: 2854700
A3: Feb | B3: 2293250
A4: Mar | B4: 2036600
A5: Apr | B5: 2203000
A6: May | B6: 2096950
A7: Jun | B7: 2133100
A8: Jul | B8: 2122150
A9: Aug | B9: 2047000
A10: Sep | B10: 2094500
A11: Oct | B11: 2385450
A12: Nov | B12: 2005900
A13: Dec | B13: 2012950
A14: Grand Total | B14: 26285550

Sheet Sales by Category
A1: Row Labels | B1: Sum of Total Sales
A2: Beauty | B2: 733000
A3: Electronics | B3: 19344850
A4: Fashion | B4: 1890700
A5: Home & Kitchen | B5: 2364100
A6: Sports | B6: 1952900
A7: Grand Total | B7: 26285550

Sheet Sales by Region
A3: Row Labels | B3: Sum of Total Sales
A4: East | B4: 4950900
A5: North | B5: 5579750
A6: South | B6: 10271750
A7: West | B7: 5483150
A8: Grand Total | B8: 26285550

Sheet Raw Data
A1: Order ID | B1: Customer ID | C1: Order Date | D1: Region | E1: City | F1: Category | G1: Product | H1: Quantity | I1: Unit Price | J1: Payment Method | K1: Order Status | L1: Total Sales
A2: ORD10001 | B2: CUST0088 | C2: 45757 | D2: South | E2: Vijayawada | F2: Home & Kitchen | G2: Table Lamp | H2: 1 | I2: 5500 | J2: UPI | K2: Delivered | L2: =H2*I2 -> 5500
A3: ORD10002 | B3: CUST0161 | C3: 45971 | D3: South | E3: Bengaluru | F3: Electronics | G3: Monitor | H3: 4 | I3: 47100 | J3: UPI | K3: Returned | L3: =H3*I3 -> 188400
A4: ORD10003 | B4: CUST0190 | C4: 45832 | D4: South | E4: Chennai | F4: Fashion | G4: Backpack | H4: 1 | I4: 5050 | J4: UPI | K4: Delivered | L4: =H4*I4 -> 5050
A5: ORD10004 | B5: CUST0274 | C5: 45746 | D5: North | E5: Chandigarh | F5: Fashion | G5: Backpack | H5: 3 | I5: 3950 | J5: Debit Card | K5: Delivered | L5: =H5*I5 -> 11850
A6: ORD10005 | B6: CUST0264 | C6: 45692 | D6: North | E6: Jaipur | F6: Sports | G6: Cricket Bat | H6: 2 | I6: 1450 | J6: Credit Card | K6: Delivered | L6: =H6*I6 -> 2900
A7: ORD10006 | B7: CUST0191 | C7: 45875 | D7: South | E7: Vijayawada | F7: Sports | G7: Running Shoes | H7: 2 | I7: 3450 | J7: Credit Card | K7: Delivered | L7: =H7*I7 -> 6900
A8: ORD10007 | B8: CUST0190 | C8: 45953 | D8: East | E8: Bhubaneswar | F8: Home & Kitchen | G8: Air Fryer | H8: 1 | I8: 6600 | J8: Credit Card | K8: Delivered | L8: =H8*I8 -> 6600
A9: ORD10008 | B9: CUST0157 | C9: 45672 | D9: South | E9: Hyderabad | F9: Sports | G9: Dumbbells | H9: 4 | I9: 6050 | J9: Debit Card | K9: Delivered | L9: =H9*I9 -> 24200
A10: ORD10009 | B10: CUST0392 | C10: 45820 | D10: East | E10: Guwahati | F10: Electronics | G10: Laptop | H10: 1 | I10: 26100 | J10: UPI | K10: Delivered | L10: =H10*I10 -> 26100
A11: ORD10010 | B11: CUST0033 | C11: 45705 | D11: South | E11: Chennai | F11: Beauty | G11: Moisturizer | H11: 4 | I11: 3350 | J11: Cash on Delivery | K11: Delivered | L11: =H11*I11 -> 13400
A12: ORD10011 | B12: CUST0131 | C12: 45914 | D12: West | E12: Surat | F12: Home & Kitchen | G12: Table Lamp | H12: 2 | I12: 2650 | J12: Credit Card | K12: Returned | L12: =H12*I12 -> 5300
A13: ORD10012 | B13: CUST0241 | C13: 45709 | D13: North | E13: Lucknow | F13: Beauty | G13: Moisturizer | H13: 1 | I13: 750 | J13: UPI | K13: Cancelled | L13: =H13*I13 -> 750
... A26: ORD10025 | B26: CUST0310 | C26: 45820 | D26: South | E26: Hyderabad | F26: Fashion | G26: Sneakers | H26: 1 | I26: 5450 | J26: UPI | K26: Delivered | L26: =H26*I26 -> 5450
A27: ORD10026 | C27: 45852 | D27: South | E27: Vijayawada | F27: Fashion | G27: T-Shirt | H27: 1 | I27: 2200 | J27: Debit Card | K27: Delivered | L27: =H27*I27 -> 2200
A28: ORD10027 | B28: CUST0365 | C28: 45708 | D28: North | E28: Lucknow | F28: Fashion | G28: T-Shirt | H28: 1 | I28: 3200 | J28: UPI | K28: Returned | L28: =H28*I28 -> 3200
A29: ORD10028 | B29: CUST0317 | C29: 45961 | D29: North | E29: Delhi | F29: Sports | G29: Football | H29: 2 | I29: 5300 | J29: Credit Card | K29: Delivered | L29: =H29*I29 -> 10600
A30: ORD10029 | B30: CUST0099 | C30: 45890 | D30: West | E30: Surat | F30: Home & Kitchen | G30: Water Bottle | H30: 4 | I30: 1800 | J30: Net Banking | K30: Cancelled | L30: =H30*I30 -> 7200
A31: ORD10030 | B31: CUST0416 | C31: 45818 | D31: North | E31: Delhi | F31: Sports | G31: Dumbbells | H31: 5 | I31: 5950 | J31: UPI | K31: Delivered | L31: =H31*I31 -> 29750
A32: ORD10031 | B32: CUST0431 | C32: 45999 | D32: North | E32: Lucknow | F32: Home & Kitchen | G32: Air Fryer | H32: 4 | I32: 7650 | J32: UPI | K32: Delivered | L32: =H32*I32 -> 30600
A33: ORD10032 | B33: CUST0170 | C33: 45904 | D33: South | E33: Bengaluru | F33: Home & Kitchen | G33: Water Bottle | H33: 2 | I33: 6750 | J33: Debit Card | K33: Delivered | L33: =H33*I33 -> 13500
A34: ORD10033 | B34: CUST0264 | C34: 45799 | D34: East | E34: Kolkata | F34: Home & Kitchen | G34: Air Fryer | H34: 1 | I34: 950 | J34: Debit Card | K34: Delivered | L34: =H34*I34 -> 950
A35: ORD10034 | B35: CUST0125 | C35: 45807 | D35: North | E35: Chandigarh | F35: Sports | G35: Running Shoes | H35: 1 | I35: 6000 | J35: Credit Card | K35: Delivered | L35: =H35*I35 -> 6000
A36: ORD10035 | B36: CUST0060 | C36: 45765 | D36: South | E36: Bengaluru | F36: Fashion | G36: T-Shirt | H36: 2 | I36: 2700 | J36: UPI | K36: Shipped | L36: =H36*I36 -> 5400
A37: ORD10036 | B37: CUST0269 | C37: 45781 | D37: East | E37: Guwahati | F37: Fashion | G37: Backpack | H37: 2 | I37: 4450 | J37: Debit Card | K37: Delivered | L37: =H37*I37 -> 8900
A38: ORD10037 | B38: CUST0318 | C38: 45936 | D38: West | E38: Ahmedabad | F38: Beauty | G38: Moisturizer | H38: 2 | I38: 2300 | J38: UPI | K38: Delivered | L38: =H38*I38 -> 4600
A39: ORD10038 | B39: CUST0089 | C39: 45894 | D39: North | E39: Jaipur | F39: Home & Kitchen | G39: Cookware Set | H39: 1 | I39: 8250 | J39: UPI | K39: Delivered | L39: =H39*I39 -> 8250
... A199: ORD10198 | B199: CUST0436 | C199: 45671 | D199: West | E199: Pune | F199: Home & Kitchen | G199: Air Fryer | H199: 3 | I199: 7950 | J199: Cash on Delivery | K199: Shipped | L199: =H199*I199 -> 23850
A200: ORD10199 | B200: CUST0025 | C200: 45938 | D200: South | E200: Chennai | F200: Electronics | G200: Headphones | H200: 1 | I200: 45400 | K200: Delivered | L200: =H200*I200 -> 45400
A201: ORD10200 | B201: CUST0425 | C201: 45682 | D201: East | E201: Bhubaneswar | F201: Home & Kitchen | G201: Mixer Grinder | H201: 3 | I201: 1450 | J201: Cash on Delivery | K201: Delivered | L201: =H201*I201 -> 4350
A202: ORD10201 | B202: CUST0128 | C202: 45753 | D202: South | E202: Bengaluru | F202: Fashion | G202: Jeans | H202: 1 | I202: 4250 | J202: UPI | K202: Delivered | L202: =H202*I202 -> 4250
A203: ORD10202 | B203: CUST0151 | C203: 45944 | D203: North | E203: Bengaluru | F203: Fashion | G203: Backpack | H203: 1 | I203: 6850 | J203: UPI | K203: Delivered | L203: =H203*I203 -> 6850
A204: ORD10203 | B204: CUST0083 | C204: 45756 | D204: South | E204: Hyderabad | F204: Electronics | G204: Monitor | H204: 5 | I204: 4450 | J204: UPI | K204: Delivered | L204: =H204*I204 -> 22250
A205: ORD10204 | B205: CUST0040 | C205: 45930 | D205: South | E205: Chennai | F205: Electronics | G205: Keyboard | H205: 2 | I205: 12150 | J205: Debit Card | K205: Delivered | L205: =H205*I205 -> 24300
A206: ORD10205 | B206: CUST0191 | C206: 45719 | D206: South | E206: Vijayawada | F206: Electronics | G206: Keyboard | H206: 3 | I206: 42850 | J206: Debit Card | K206: Shipped | L206: =H206*I206 -> 128550
A207: ORD10206 | B207: CUST0183 | C207: 45719 | D207: South | E207: Vijayawada | F207: Fashion | G207: Sneakers | H207: 1 | I207: 4050 | J207: Credit Card | K207: Returned | L207: =H207*I207 -> 4050
A208: ORD10207 | B208: CUST0213 | C208: 45838 | D208: West | E208: Pune | F208: Home & Kitchen | G208: Table Lamp | H208: 2 | I208: 1900 | J208: UPI | K208: Shipped | L208: =H208*I208 -> 3800
A209: ORD10208 | B209: CUST0183 | C209: 45774 | D209: South | E209: Hyderabad | F209: Beauty | G209: Hair Dryer | H209: 2 | I209: 750 | J209: Credit Card | K209: Shipped | L209: =H209*I209 -> 1500
A210: ORD10209 | B210: CUST0422 | C210: 45699 | D210: East | E210: Guwahati | F210: Home & Kitchen | G210: Cookware Set | H210: 1 | I210: 6700 | J210: Credit Card | K210: Delivered | L210: =H210*I210 -> 6700
A211: ORD10210 | B211: CUST0029 | C211: 45754 | D211: South | E211: Vijayawada | F211: Beauty | G211: Hair Dryer | H211: 1 | I211: 4000 | J211: Debit Card | K211: Delivered | L211: =H211*I211 -> 4000
A212: ORD10211 | B212: CUST0200 | C212: 45736 | D212: South | E212: Vijayawada | F212: Sports | G212: Cricket Bat | H212: 2 | I212: 4900 | J212: Debit Card | K212: Cancelled | L212: =H212*I212 -> 9800
... A359: ORD10358 | B359: CUST0022 | C359: 45811 | D359: West | E359: Pune | F359: Fashion | G359: Sneakers | H359: 1 | I359: 4050 | J359: UPI | K359: Delivered | L359: =H359*I359 -> 4050
A360: ORD10359 | B360: CUST0367 | C360: 45979 | D360: South | E360: Bengaluru | F360: Fashion | G360: Sneakers | H360: 1 | I360: 900 | K360: Delivered | L360: =H360*I360 -> 900
A361: ORD10360 | B361: CUST0233 | C361: 45757 | D361: West | E361: Pune | F361: Electronics | G361: Smartphone | H361: 2 | I361: 16850 | J361: Debit Card | K361: Delivered | L361: =H361*I361 -> 33700
A362: ORD10361 | B362: CUST0435 | C362: 45705 | D362: East | E362: Kolkata | F362: Electronics | G362: Smartphone | H362: 1 | I362: 8250 | J362: Debit Card | K362: Delivered | L362: =H362*I362 -> 8250
A363: ORD10362 | B363: CUST0137 | C363: 45821 | D363: West | E363: Mumbai | F363: Electronics | G363: Keyboard | H363: 2 | I363: 3950 | J363: Credit Card | K363: Cancelled | L363: =H363*I363 -> 7900
A364: ORD10363 | B364: CUST0330 | C364: 45940 | D364: North | E364: Delhi | F364: Sports | G364: Cricket Bat | H364: 2 | I364: 6350 | J364: UPI | K364: Delivered | L364: =H364*I364 -> 12700
A365: ORD10364 | B365: CUST0073 | C365: 45905 | D365: East | E365: Kolkata | F365: Home & Kitchen | G365: Water Bottle | H365: 1 | I365: 8250 | J365: UPI | K365: Delivered | L365: =H365*I365 -> 8250
A366: ORD10365 | B366: CUST0111 | C366: 45704 | D366: West | E366: Pune | F366: Electronics | G366: Monitor | H366: 1 | I366: 45750 | J366: Debit Card | K366: Shipped | L366: =H366*I366 -> 45750
A367: ORD10366 | B367: CUST0318 | C367: 45971 | D367: South | E367: Hyderabad | F367: Electronics | G367: Laptop | H367: 4 | I367: 5650 | J367: UPI | K367: Delivered | L367: =H367*I367 -> 22600
A368: ORD10367 | B368: CUST0077 | C368: 45831 | D368: South | E368: Chennai | F368: Fashion | G368: Jeans | H368: 3 | I368: 6750 | J368: Cash on Delivery | K368: Cancelled | L368: =H368*I368 -> 20250
A369: ORD10368 | B369: CUST0390 | C369: 45764 | D369: South | E369: Chennai | F369: Home & Kitchen | G369: Mixer Grinder | H369: 1 | I369: 4800 | J369: Credit Card | K369: Cancelled | L369: =H369*I369 -> 4800
A370: ORD10369 | B370: CUST0445 | C370: 45715 | D370: East | E370: Kolkata | F370: Fashion | G370: T-Shirt | H370: 2 | I370: 7200 | J370: Debit Card | K370: Delivered | L370: =H370*I370 -> 14400
A371: ORD10370 | B371: CUST0354 | C371: 45720 | D371: East | E371: Guwahati | F371: Electronics | G371: Keyboard | H371: 2 | I371: 29150 | J371: Net Banking | K371: Delivered | L371: =H371*I371 -> 58300
A372: ORD10371 | B372: CUST0324 | C372: 45864 | D372: West | E372: Mumbai | F372: Home & Kitchen | G372: Water Bottle | H372: 2 | I372: 2900 | J372: UPI | K372: Delivered | L372: =H372*I372 -> 5800
... A433: ORD10432 | B433: CUST0390 | C433: 45999 | D433: West | E433: Mumbai | F433: Electronics | G433: Monitor | H433: 2 | I433: 15950 | J433: Credit Card | K433: Cancelled | L433: =H433*I433 -> 31900
A434: ORD10433 | B434: CUST0305 | C434: 45806 | D434: West | F434: Electronics | G434: Headphones | H434: 3 | I434: 34450 | J434: UPI | K434: Delivered | L434: =H434*I434 -> 103350
A435: ORD10434 | B435: CUST0119 | C435: 45950 | D435: West | E435: Ahmedabad | F435: Sports | G435: Football | H435: 2 | I435: 6300 | J435: UPI | K435: Shipped | L435: =H435*I435 -> 12600
A436: ORD10435 | B436: CUST0105 | C436: 45885 | D436: South | E436: Hyderabad | F436: Sports | G436: Running Shoes | H436: 4 | I436: 3200 | J436: UPI | K436: Delivered | L436: =H436*I436 -> 12800
A437: ORD10436 | B437: CUST0304 | C437: 45953 | D437: South | E437: Chennai | F437: Fashion | G437: Sneakers | H437: 1 | I437: 1500 | J437: Cash on Delivery | K437: Delivered | L437: =H437*I437 -> 1500
A438: ORD10437 | B438: CUST0184 | C438: 45733 | D438: South | E438: Vijayawada | F438: Fashion | G438: Backpack | H438: 1 | I438: 3850 | J438: UPI | K438: Delivered | L438: =H438*I438 -> 3850
A439: ORD10438 | B439: CUST0404 | C439: 46017 | D439: North | E439: Jaipur | F439: Electronics | G439: Headphones | H439: 1 | I439: 12900 | J439: UPI | K439: Cancelled | L439: =H439*I439 -> 12900
A440: ORD10439 | B440: CUST0181 | C440: 45701 | D440: South | E440: Chennai | F440: Fashion | G440: Sneakers | H440: 1 | I440: 6150 | J440: UPI | K440: Delivered | L440: =H440*I440 -> 6150
A441: ORD10440 | B441: CUST0129 | C441: 45903 | D441: East | E441: Bhubaneswar | F441: Home & Kitchen | G441: Air Fryer | H441: 4 | I441: 8100 | J441: UPI | K441: Delivered | L441: =H441*I441 -> 32400
A442: ORD10441 | B442: CUST0372 | C442: 45951 | D442: South | E442: Hyderabad | F442: Electronics | G442: Monitor | H442: 3 | I442: 56200 | J442: UPI | K442: Delivered | L442: =H442*I442 -> 168600
A443: ORD10442 | B443: CUST0070 | C443: 45770 | D443: South | E443: Vijayawada | F443: Fashion | G443: Jeans | H443: 2 | I443: 6000 | J443: Credit Card | K443: Delivered | L443: =H443*I443 -> 12000
A444: ORD10443 | B444: CUST0192 | C444: 45697 | D444: West | E444: Surat | F444: Electronics | G444: Keyboard | H444: 1 | I444: 38100 | J444: Cash on Delivery | K444: Delivered | L444: =H444*I444 -> 38100
A445: ORD10444 | B445: CUST0311 | C445: 45694 | D445: East | E445: Guwahati | F445: Home & Kitchen | G445: Mixer Grinder | H445: 3 | I445: 7500 | J445: UPI | K445: Delivered | L445: =H445*I445 -> 22500
A446: ORD10445 | B446: CUST0030 | C446: 45924 | D446: West | E446: Mumbai | F446: Electronics | G446: Headphones | H446: 2 | I446: 5000 | J446: Debit Card | K446: Delivered | L446: =H446*I446 -> 10000
... A545: ORD10544 | B545: CUST0021 | C545: 45711 | D545: South | E545: Vijayawada | F545: Electronics | G545: Monitor | H545: 3 | I545: 52300 | J545: UPI | K545: Returned | L545: =H545*I545 -> 156900
A546: ORD10545 | B546: CUST0157 | C546: 45848 | D546: West | F546: Fashion | G546: Sneakers | H546: 3 | I546: 2600 | J546: Cash on Delivery | K546: Returned | L546: =H546*I546 -> 7800
A547: ORD10546 | B547: CUST0230 | C547: 45829 | D547: West | E547: Ahmedabad | F547: Electronics | G547: Keyboard | H547: 1 | I547: 11550 | J547: Debit Card | K547: Delivered | L547: =H547*I547 -> 11550
A548: ORD10547 | B548: CUST0209 | C548: 45884 | D548: East | E548: Kolkata | F548: Electronics | G548: Monitor | H548: 1 | I548: 41600 | J548: Credit Card | K548: Delivered | L548: =H548*I548 -> 41600
A549: ORD10548 | B549: CUST0095 | C549: 45930 | D549: West | E549: Pune | F549: Beauty | G549: Moisturizer | H549: 1 | I549: 2150 | J549: Debit Card | K549: Cancelled | L549: =H549*I549 -> 2150
A550: ORD10549 | B550: CUST0050 | C550: 45949 | D550: South | E550: Bengaluru | F550: Home & Kitchen | G550: Cookware Set | H550: 1 | I550: 2950 | J550: UPI | K550: Delivered | L550: =H550*I550 -> 2950
A551: ORD10550 | B551: CUST0222 | C551: 45898 | D551: West | E551: Mumbai | F551: Electronics | G551: Monitor | H551: 3 | I551: 19900 | J551: Credit Card | K551: Delivered | L551: =H551*I551 -> 59700
A552: ORD10551 | B552: CUST0415 | C552: 45849 | D552: South | E552: Vijayawada | F552: Electronics | G552: Smartphone | H552: 1 | I552: 34600 | J552: UPI | K552: Delivered | L552: =H552*I552 -> 34600
A553: ORD10552 | B553: CUST0445 | C553: 45902 | D553: South | E553: Hyderabad | F553: Fashion | G553: Sneakers | H553: 3 | I553: 3850 | J553: Credit Card | K553: Delivered | L553: =H553*I553 -> 11550
A554: ORD10553 | B554: CUST0132 | C554: 45742 | D554: East | E554: Bhubaneswar | F554: Beauty | G554: Hair Dryer | H554: 1 | I554: 3450 | J554: UPI | K554: Delivered | L554: =H554*I554 -> 3450
A555: ORD10554 | B555: CUST0201 | C555: 45854 | D555: East | E555: Kolkata | F555: Fashion | G555: T-Shirt | H555: 1 | I555: 2350 | J555: Credit Card | K555: Delivered | L555: =H555*I555 -> 2350
A556: ORD10555 | B556: CUST0251 | C556: 45754 | D556: South | E556: Vijayawada | F556: Sports | G556: Cricket Bat | H556: 1 | I556: 5350 | J556: Cash on Delivery | K556: Delivered | L556: =H556*I556 -> 5350
A557: ORD10556 | B557: CUST0032 | C557: 45818 | D557: South | E557: Hyderabad | F557: Beauty | G557: Face Wash | H557: 2 | I557: 750 | J557: UPI | K557: Delivered | L557: =H557*I557 -> 1500
A558: ORD10557 | B558: CUST0056 | C558: 45770 | D558: West | E558: Surat | F558: Beauty | G558: Face Wash | H558: 1 | I558: 4950 | J558: UPI | K558: Delivered | L558: =H558*I558 -> 4950
... A851: ORD10850 | B851: CUST0074 | C851: 45844 | D851: South | E851: Vijayawada | F851: Home & Kitchen | G851: Air Fryer | H851: 4 | I851: 7700 | J851: UPI | K851: Cancelled | L851: =H851*I851 -> 30800
A852: ORD10851 | C852: 45855 | D852: East | E852: Bhubaneswar | F852: Fashion | G852: Backpack | H852: 1 | I852: 5850 | J852: UPI | K852: Delivered | L852: =H852*I852 -> 5850
A853: ORD10852 | B853: CUST0288 | C853: 45883 | D853: South | E853: Bengaluru | F853: Electronics | G853: Headphones | H853: 1 | I853: 29500 | J853: Cash on Delivery | K853: Delivered | L853: =H853*I853 -> 29500
A854: ORD10853 | B854: CUST0289 | C854: 45695 | D854: North | E854: Jaipur | F854: Electronics | G854: Smartphone | H854: 1 | I854: 43150 | J854: Debit Card | K854: Returned | L854: =H854*I854 -> 43150
A855: ORD10854 | B855: CUST0433 | C855: 45713 | D855: South | E855: Hyderabad | F855: Electronics | G855: Headphones | H855: 3 | I855: 34600 | J855: Cash on Delivery | K855: Cancelled | L855: =H855*I855 -> 103800
A856: ORD10855 | B856: CUST0049 | C856: 45804 | D856: East | E856: Bhubaneswar | F856: Sports | G856: Dumbbells | H856: 2 | I856: 1500 | J856: UPI | K856: Returned | L856: =H856*I856 -> 3000
A857: ORD10856 | B857: CUST0332 | C857: 45788 | D857: East | E857: Kolkata | F857: Home & Kitchen | G857: Table Lamp | H857: 1 | I857: 1400 | J857: UPI | K857: Cancelled | L857: =H857*I857 -> 1400
A858: ORD10857 | B858: CUST0148 | C858: 45887 | D858: West | E858: Pune | F858: Beauty | G858: Shampoo | H858: 1 | I858: 950 | J858: Debit Card | K858: Delivered | L858: =H858*I858 -> 950
A859: ORD10858 | B859: CUST0271 | C859: 45751 | D859: North | E859: Chandigarh | F859: Fashion | G859: Jeans | H859: 1 | I859: 7000 | J859: Debit Card | K859: Delivered | L859: =H859*I859 -> 7000
A860: ORD10859 | B860: CUST0237 | C860: 45884 | D860: West | E860: Ahmedabad | F860: Beauty | G860: Shampoo | H860: 2 | I860: 1100 | J860: UPI | K860: Shipped | L860: =H860*I860 -> 2200
A861: ORD10860 | B861: CUST0292 | C861: 45967 | D861: South | E861: Chennai | F861: Fashion | G861: Watch | H861: 1 | I861: 7400 | J861: Net Banking | K861: Delivered | L861: =H861*I861 -> 7400
A862: ORD10861 | B862: CUST0283 | C862: 45694 | D862: North | E862: Jaipur | F862: Home & Kitchen | G862: Mixer Grinder | H862: 2 | I862: 1350 | J862: Debit Card | K862: Delivered | L862: =H862*I862 -> 2700
A863: ORD10862 | B863: CUST0154 | C863: 45807 | D863: North | E863: Chandigarh | F863: Fashion | G863: Sneakers | H863: 1 | I863: 7900 | J863: Debit Card | K863: Delivered | L863: =H863*I863 -> 7900
A864: ORD10863 | B864: CUST0137 | C864: 45846 | D864: North | E864: Chandigarh | F864: Beauty | G864: Perfume | H864: 1 | I864: 2050 | J864: Debit Card | K864: Delivered | L864: =H864*I864 -> 2050
... A867: ORD10866 | B867: CUST0126 | C867: 45704 | D867: East | E867: Patna | F867: Home & Kitchen | G867: Mixer Grinder | H867: 1 | I867: 2750 | J867: Debit Card | K867: Delivered | L867: =H867*I867 -> 2750
A868: ORD10867 | B868: CUST0337 | C868: 45752 | D868: South | F868: Fashion | G868: Watch | H868: 1 | I868: 1400 | J868: Debit Card | K868: Delivered | L868: =H868*I868 -> 1400
A869: ORD10868 | B869: CUST0090 | C869: 45968 | D869: West | E869: Ahmedabad | F869: Electronics | G869: Headphones | H869: 5 | I869: 43750 | J869: UPI | K869: Delivered | L869: =H869*I869 -> 218750
...

Sheet Dataset Info
A1: Item | B1: Details
A2: Project | B2: E-commerce Sales Dashboard
A3: Dataset | B3: Synthetic practice dataset
A4: Rows | B4: 1200
A5: Columns | B5: 12
A6: Purpose | B6: Cleaning, PivotTables, KPIs, dashboard and business insights
A7: Note | B7: Created for portfolio practice; not real company data.
